cfspeedtest/__init__.py
cfspeedtest/__main__.py
cfspeedtest/cloudflare.py
cfspeedtest/logger.py
cfspeedtest/version.py
cloudflarepycli-2.0.2.dist-info/LICENSE
cloudflarepycli-2.0.2.dist-info/METADATA
cloudflarepycli-2.0.2.dist-info/WHEEL
cloudflarepycli-2.0.2.dist-info/entry_points.txt
cloudflarepycli-2.0.2.dist-info/top_level.txt
cloudflarepycli-2.0.2.dist-info/RECORD
