Metadata-Version: 2.1
Name: cloudflarepycli
Version: 2.0.2
Summary: Python CLI and utiltiies for retrieving network performance statistics.
Author-email: Tom Evslin <tevslin@gmail.com>, Martin Brose <nitramesorb@gmail.com>
License: GNU GENERAL PUBLIC LICENSE
Project-URL: Homepage, https://github.com/martinbrose/cloudflarepycli
Project-URL: Issues, https://github.com/martinbrose/cloudflarepycli/issues
Keywords: speedtest,cloudflare,latency,jitter
Classifier: Programming Language :: Python :: 3
Classifier: License :: OSI Approved :: GNU General Public License v3 (GPLv3)
Classifier: Operating System :: OS Independent
Requires-Python: >=3.8
License-File: LICENSE
Requires-Dist: requests >=2.32.3
